uetools/commands/__init__.py
uetools/commands/fmt.py
uetools/commands/init.py
uetools/commands/editor/__init__.py
uetools/commands/editor/client.py
uetools/commands/editor/cook.py
uetools/commands/editor/editor.py
uetools/commands/editor/game.py
uetools/commands/editor/localize.py
uetools/commands/editor/ml.py
uetools/commands/editor/open.py
uetools/commands/editor/resavepackages.py
uetools/commands/editor/server.py
uetools/commands/editor/worldpartition.py
uetools/commands/editor/templates/Localization/TargetName.ini
uetools/commands/engine/__init__.py
uetools/commands/engine/add.py
uetools/commands/engine/update.py
uetools/commands/game/__init__.py
uetools/commands/game/client.py
uetools/commands/game/game.py
uetools/commands/game/server.py
uetools/commands/game/stop.py
uetools/commands/gitlab/__init__.py
uetools/commands/gitlab/publish.py
uetools/commands/gitlab/zip.py
uetools/commands/plugin/__init__.py
uetools/commands/plugin/class.py
uetools/commands/plugin/disable.py
uetools/commands/plugin/finalize.py
uetools/commands/plugin/install.py
uetools/commands/plugin/list.py
uetools/commands/plugin/new.py
uetools/commands/plugin/package.py
uetools/commands/plugin/templates/PluginTemplate/cookiecutter.json
uetools/commands/plugin/templates/PluginTemplate/{{cookiecutter.plugin_name}}/.gitignore
uetools/commands/plugin/templates/PluginTemplate/{{cookiecutter.plugin_name}}/LICENSE
uetools/commands/plugin/templates/PluginTemplate/{{cookiecutter.plugin_name}}/README.rst
uetools/commands/plugin/templates/PluginTemplate/{{cookiecutter.plugin_name}}/setup.py
uetools/commands/plugin/templates/PluginTemplate/{{cookiecutter.plugin_name}}/{{cookiecutter.plugin_name}}.uplugin
uetools/commands/plugin/templates/PluginTemplate/{{cookiecutter.plugin_name}}/.github/FUNDING.yml
uetools/commands/plugin/templates/PluginTemplate/{{cookiecutter.plugin_name}}/.github/ISSUE_TEMPLATE/bug_report.md
uetools-2.1.1.dist-info/LICENSE
uetools-2.1.1.dist-info/METADATA
uetools-2.1.1.dist-info/WHEEL
uetools-2.1.1.dist-info/entry_points.txt
uetools-2.1.1.dist-info/top_level.txt
uetools-2.1.1.dist-info/zip-safe
uetools-2.1.1.dist-info/RECORD
