Metadata-Version: 2.1
Name: uetools
Version: 2.1.1
Summary: Tools for Unreal Engine
Home-page: https://uetools.readthedocs.io
Author: Pierre Delaunay
Author-email: pierre@delaunay.io
License: BSD-3-Clause
Classifier: License :: OSI Approved :: BSD License
Classifier: Programming Language :: Python :: 3.8
Classifier: Programming Language :: Python :: 3.9
Classifier: Programming Language :: Python :: 3.10
Classifier: Programming Language :: Python :: 3.11
Classifier: Programming Language :: Python :: 3.12
Classifier: Operating System :: OS Independent
Classifier: Development Status :: 4 - Beta
Requires-Python: >=3.8
License-File: LICENSE
Requires-Dist: appdirs
Requires-Dist: colorama
Requires-Dist: cookiecutter
Requires-Dist: GitPython
Requires-Dist: hjson
Requires-Dist: importlib-resources
Requires-Dist: tqdm
Requires-Dist: argklass >=1.4.4
Provides-Extra: all
Requires-Dist: gym ; extra == 'all'
Requires-Dist: msgpack ; extra == 'all'
Requires-Dist: numpy ; extra == 'all'
Provides-Extra: ml
Requires-Dist: msgpack ; extra == 'ml'
Requires-Dist: numpy ; extra == 'ml'
Requires-Dist: gym ; extra == 'ml'
